cli/__init__.py
cli/cli.py
cli/command.py
cli/interactive.py
cli/menu.py
cli/utils.py
climenus-0.1.3.dist-info/LICENSE
climenus-0.1.3.dist-info/METADATA
climenus-0.1.3.dist-info/WHEEL
climenus-0.1.3.dist-info/top_level.txt
climenus-0.1.3.dist-info/RECORD
