Metadata-Version: 2.2
Name: climenus
Version: 0.1.3
Summary: A simple framework for building interactive CLI menus in Python
Home-page: https://github.com/vencordthemer/simplecli
Author: VencordThemer
Author-email: vencordthemer@users.noreply.github.com
Project-URL: Bug Tracker, https://github.com/vencordthemer/simplecli/issues
Keywords: cli,menu,terminal,console,interactive
Classifier: Programming Language :: Python :: 3
Classifier: License :: OSI Approved :: MIT License
Classifier: Operating System :: OS Independent
Classifier: Intended Audience :: Developers
Classifier: Topic :: Software Development :: Libraries :: Python Modules
Classifier: Topic :: Utilities
Requires-Python: >=3.6
License-File: LICENSE
Dynamic: author
Dynamic: author-email
Dynamic: classifier
Dynamic: description
Dynamic: description-content-type
Dynamic: home-page
Dynamic: keywords
Dynamic: project-url
Dynamic: requires-python
Dynamic: summary
